README.md
setup.py
yama_util/__init__.py
yama_util/temp.py
yama_util/temp2.py
yama_util.egg-info/PKG-INFO
yama_util.egg-info/SOURCES.txt
yama_util.egg-info/dependency_links.txt
yama_util.egg-info/top_level.txt